desolver/__init__.py
desolver/differential_system.py
desolver/backend/__init__.py
desolver/backend/autoray_backend.py
desolver/backend/common.py
desolver/backend/load_backend.py
desolver/backend/numpy_backend.py
desolver/backend/torch_backend.py
desolver/backend/tests/__init__.py
desolver/backend/tests/test_backend.py
desolver/exception_types/__init__.py
desolver/exception_types/exception_types.py
desolver/exception_types/tests/__init__.py
desolver/exception_types/tests/test_exception_types.py
desolver/integrators/__init__.py
desolver/integrators/explicit_integration_schemes.py
desolver/integrators/implicit_integration_schemes.py
desolver/integrators/integrator_template.py
desolver/integrators/integrator_types.py
desolver/integrators/utilities.py
desolver/integrators/components/__init__.py
desolver/integrators/components/runge_kutta_methods.py
desolver/integrators/tests/test_integrators.py
desolver/tests/__init__.py
desolver/tests/common.py
desolver/tests/test_dense_output.py
desolver/tests/test_differential_system.py
desolver/tests/test_event_detection.py
desolver/utilities/__init__.py
desolver/utilities/interpolation.py
desolver/utilities/optimizer.py
desolver/utilities/utilities.py
desolver/utilities/tests/common.py
desolver/utilities/tests/test_interpolation.py
desolver/utilities/tests/test_optimizer.py
desolver/utilities/tests/test_utilities.py
desolver-5.1.0.dist-info/METADATA
desolver-5.1.0.dist-info/WHEEL
desolver-5.1.0.dist-info/licenses/LICENSE
desolver-5.1.0.dist-info/RECORD
