Metadata-Version: 2.4
Name: desolver
Version: 5.1.0
Summary: Differential Equation System Solver
Project-URL: Homepage, https://github.com/Microno95/desolver.git
Project-URL: Documentation, https://desolver.readthedocs.io/
Project-URL: Repository, https://github.com/Microno95/desolver.git
Project-URL: Issues, https://github.com/Microno95/desolver/issues
Project-URL: Changelog, https://github.com/me/spam/blob/master/CHANGELOG.md
Author-email: Ekin Ozturk' <ekin.ozturk@alumni.utoronto.ca>
Maintainer-email: Ekin Ozturk' <ekin.ozturk@alumni.utoronto.ca>
License-Expression: MIT
License-File: LICENSE
Keywords: differential equation,differential system,non-linear ode,ode solver,ode system
Classifier: Development Status :: 5 - Production/Stable
Classifier: Environment :: Console
Classifier: Intended Audience :: Developers
Classifier: Intended Audience :: Education
Classifier: Intended Audience :: End Users/Desktop
Classifier: Intended Audience :: Science/Research
Classifier: License :: OSI Approved :: MIT License
Classifier: Programming Language :: Python :: 3.10
Classifier: Programming Language :: Python :: 3.11
Classifier: Programming Language :: Python :: 3.12
Classifier: Topic :: Scientific/Engineering :: Mathematics
Requires-Python: >=3.10
Requires-Dist: autoray>=0.7.0
Requires-Dist: einops>=0.8.0
Requires-Dist: numpy>=2
Requires-Dist: scipy>=1.15.0
Requires-Dist: tqdm>=4.47.0
Provides-Extra: build
Requires-Dist: hatch; extra == 'build'
Provides-Extra: test
Requires-Dist: coverage; extra == 'test'
Requires-Dist: pytest>=5.4.3; extra == 'test'
Provides-Extra: torch
Requires-Dist: torch>=2.5.0; extra == 'torch'
